game_design.v
// game_design.v (3 enemies, hit counter, auto-random spawns, Verilog-2001 safe)

`timescale 1ns/1ps

module game_design #(
    parameter AUTO_SPAWN = 1   // 1 = game mode, 0 = deterministic testbench mode
)(
    input  wire clk,
    input  wire rst_n,
    input  wire left,
    input  wire right,
    input  wire shoot,

    // external testbench spawn
    input  wire        enemy_spawn,
    input  wire [4:0]  enemy_init_x,
    input  wire [3:0]  enemy_init_y,

    // outputs
    output reg  [4:0]  player_x,
    output reg  [3:0]  player_y,
    output reg  [4:0]  bullet_x,
    output reg  [3:0]  bullet_y,
    output reg         bullet_active,

    output reg  [4:0]  enemy0_x,
    output reg  [3:0]  enemy0_y,
    output reg         enemy0_active,

    output reg  [4:0]  enemy1_x,
    output reg  [3:0]  enemy1_y,
    output reg         enemy1_active,

    output reg  [4:0]  enemy2_x,
    output reg  [3:0]  enemy2_y,
    output reg         enemy2_active,

    output reg         hit,
    output reg  [7:0]  hit_count,
    output reg  [7:0]  score
);

    // constants
    localparam COLS = 20;
    localparam ROWS = 15;
    localparam PLAYER_ROW = ROWS - 1;   // y=14
    localparam BULLET_TIMER = 2;
    localparam ENEMY_TIMER  = 3;
    localparam SPAWN_TIMER  = 10;

    // counters
    reg [3:0] bullet_timer_cnt;
    reg [3:0] enemy0_timer_cnt;
    reg [3:0] enemy1_timer_cnt;
    reg [3:0] enemy2_timer_cnt;
    reg [7:0] spawn_timer_cnt;

    // simple LFSR
    reg [7:0] lfsr;

    // integers must be declared outside always blocks
    integer active_count;

    // -------------------------------
    // sequential logic
    // -------------------------------
    always @(posedge clk or negedge rst_n) begin
        if (!rst_n) begin
            player_x <= 10;
            player_y <= PLAYER_ROW[3:0];

            bullet_active <= 0;
            bullet_x <= 0;
            bullet_y <= 0;
            bullet_timer_cnt <= 0;

            enemy0_active <= 0; enemy0_x <= 0; enemy0_y <= 0; enemy0_timer_cnt <= 0;
            enemy1_active <= 0; enemy1_x <= 0; enemy1_y <= 0; enemy1_timer_cnt <= 0;
            enemy2_active <= 0; enemy2_x <= 0; enemy2_y <= 0; enemy2_timer_cnt <= 0;

            hit <= 0;
            hit_count <= 0;
            score <= 0;

            spawn_timer_cnt <= 0;
            lfsr <= 8'hA5;
        end
        else begin
            hit <= 0;

            // LFSR update
            lfsr <= {lfsr[6:0],
                     (lfsr[7] ^ lfsr[5] ^ lfsr[4] ^ lfsr[3])
                    };

            // PLAYER movement
            if (left && !right) begin
                if (player_x > 0) player_x <= player_x - 1;
            end
            else if (right && !left) begin
                if (player_x < COLS-1) player_x <= player_x + 1;
            end

            // SHOOT
            if (shoot && !bullet_active) begin
                bullet_active <= 1'b1;
                bullet_x <= player_x;
                bullet_y <= PLAYER_ROW - 1;
                bullet_timer_cnt <= 0;
            end

            // EXTERNAL enemy spawn
            if (enemy_spawn) begin
                if (!enemy0_active) begin
                    enemy0_active <= 1;
                    enemy0_x <= enemy_init_x;
                    enemy0_y <= enemy_init_y;
                    enemy0_timer_cnt <= 0;
                end
                else if (!enemy1_active) begin
                    enemy1_active <= 1;
                    enemy1_x <= enemy_init_x;
                    enemy1_y <= enemy_init_y;
                    enemy1_timer_cnt <= 0;
                end
                else if (!enemy2_active) begin
                    enemy2_active <= 1;
                    enemy2_x <= enemy_init_x;
                    enemy2_y <= enemy_init_y;
                    enemy2_timer_cnt <= 0;
                end
            end

// --------------------------------------------------------
// AUTO SPAWN CONTROL (only if AUTO_SPAWN == 1)
// --------------------------------------------------------
if (AUTO_SPAWN) begin
    spawn_timer_cnt <= spawn_timer_cnt + 1;

    if (spawn_timer_cnt >= SPAWN_TIMER) begin
        spawn_timer_cnt <= 0;

        // count active enemies
 active_count = 0;
if (enemy0_active) active_count = active_count + 1;
if (enemy1_active) active_count = active_count + 1;
if (enemy2_active) active_count = active_count + 1;


        // maintain at least 2 enemies
        if (active_count < 2) begin
            if (!enemy0_active) begin
                enemy0_active <= 1;
                enemy0_x <= (lfsr[4:0] & 5'h13);   // FIXED — NO %
                enemy0_y <= 0;
                enemy0_timer_cnt <= 0;
            end
            else if (!enemy1_active) begin
                enemy1_active <= 1;
                enemy1_x <= (lfsr[4:0] & 5'h13);   // FIXED
                enemy1_y <= 0;
                enemy1_timer_cnt <= 0;
            end
            else if (!enemy2_active) begin
                enemy2_active <= 1;
                enemy2_x <= (lfsr[4:0] & 5'h13);   // FIXED
                enemy2_y <= 0;
                enemy2_timer_cnt <= 0;
            end
        end
        else begin
            // chance to spawn 3rd enemy
            if (lfsr[0] == 1'b1 && !enemy2_active) begin
                enemy2_active <= 1;
                enemy2_x <= (lfsr[4:0] & 5'h13);   // FIXED
                enemy2_y <= 0;
                enemy2_timer_cnt <= 0;
            end
        end
    end
end



            // BULLET movement
            if (bullet_active) begin
                bullet_timer_cnt <= bullet_timer_cnt + 1;
                if (bullet_timer_cnt >= BULLET_TIMER-1) begin
                    bullet_timer_cnt <= 0;
                    if (bullet_y > 0) bullet_y <= bullet_y - 1;
                    else bullet_active <= 0;
                end
            end

            // ENEMY 0 movement
            if (enemy0_active) begin
                enemy0_timer_cnt <= enemy0_timer_cnt + 1;
                if (enemy0_timer_cnt >= ENEMY_TIMER-1) begin
                    enemy0_timer_cnt <= 0;
                    if (enemy0_y < ROWS-1) enemy0_y <= enemy0_y + 1;
                    else enemy0_active <= 0;
                end
            end

            // ENEMY 1
            if (enemy1_active) begin
                enemy1_timer_cnt <= enemy1_timer_cnt + 1;
                if (enemy1_timer_cnt >= ENEMY_TIMER-1) begin
                    enemy1_timer_cnt <= 0;
                    if (enemy1_y < ROWS-1) enemy1_y <= enemy1_y + 1;
                    else enemy1_active <= 0;
                end
            end

            // ENEMY 2
            if (enemy2_active) begin
                enemy2_timer_cnt <= enemy2_timer_cnt + 1;
                if (enemy2_timer_cnt >= ENEMY_TIMER-1) begin
                    enemy2_timer_cnt <= 0;
                    if (enemy2_y < ROWS-1) enemy2_y <= enemy2_y + 1;
                    else enemy2_active <= 0;
                end
            end

            // COLLISION DETECTION
            if (bullet_active) begin
                // enemy0
                if (enemy0_active &&
                    bullet_x == enemy0_x &&
                    bullet_y == enemy0_y) begin
                    hit <= 1;
                    bullet_active <= 0;
                    enemy0_active <= 0;
                    score <= score + 1;
                    hit_count <= hit_count + 1;
                end
                // enemy1
                else if (enemy1_active &&
                         bullet_x == enemy1_x &&
                         bullet_y == enemy1_y) begin
                    hit <= 1;
                    bullet_active <= 0;
                    enemy1_active <= 0;
                    score <= score + 1;
                    hit_count <= hit_count + 1;
                end
                // enemy2
                else if (enemy2_active &&
                         bullet_x == enemy2_x &&
                         bullet_y == enemy2_y) begin
                    hit <= 1;
                    bullet_active <= 0;
                    enemy2_active <= 0;
                    score <= score + 1;
                    hit_count <= hit_count + 1;
                end
            end

        end
    end

endmodule

snapshot_tb.v
`timescale 1ns/1ps
module snapshot_tb;

  reg clk, rst_n;
  reg left, right, shoot;
  reg enemy_spawn;
  reg [4:0] enemy_init_x;
  reg [3:0] enemy_init_y;

  wire [4:0] player_x;
  wire [3:0] player_y;
  wire [4:0] bullet_x;
  wire [3:0] bullet_y;
  wire        bullet_active;

  wire [4:0] enemy0_x, enemy1_x, enemy2_x;
  wire [3:0] enemy0_y, enemy1_y, enemy2_y;
  wire        enemy0_active, enemy1_active, enemy2_active;

  wire        hit;
  wire [7:0]  hit_count;
  wire [7:0]  score;

  game_design dut(
    .clk(clk), .rst_n(rst_n),
    .left(left), .right(right), .shoot(shoot),
    .enemy_spawn(enemy_spawn), .enemy_init_x(enemy_init_x), .enemy_init_y(enemy_init_y),
    .player_x(player_x), .player_y(player_y),
    .bullet_x(bullet_x), .bullet_y(bullet_y), .bullet_active(bullet_active),
    .enemy0_x(enemy0_x), .enemy0_y(enemy0_y), .enemy0_active(enemy0_active),
    .enemy1_x(enemy1_x), .enemy1_y(enemy1_y), .enemy1_active(enemy1_active),
    .enemy2_x(enemy2_x), .enemy2_y(enemy2_y), .enemy2_active(enemy2_active),
    .hit(hit), .hit_count(hit_count), .score(score)
  );

  initial begin clk = 0; forever #1 clk = ~clk; end

  integer cycle;
  initial begin
    $dumpfile("snapshot.vcd");
    $dumpvars(0, snapshot_tb);

    left=0; right=0; shoot=0;
    enemy_spawn=0; enemy_init_x=0; enemy_init_y=0;
    rst_n=0; #5; rst_n=1; #2;
    cycle = 0;

    #(45*2);
    left = 1; #2; left = 0;
    #(9*2);
    shoot = 1; #2; shoot = 0;
    #(12*2);
    left = 1; #2; left = 0;
    #(7*2);
    shoot = 1; #2; shoot = 0;
    #(24*2);
    shoot = 1; #2; shoot = 0;
    #(13*2);
    right = 1; #2; right = 0;
    #(10*2);
    right = 1; #2; right = 0;
    #(6*2);
    right = 1; #2; right = 0;
    #(18*2);
    left = 1; #2; left = 0;
    #(9*2);
    right = 1; #2; right = 0;
    #(9*2);
    shoot = 1; #2; shoot = 0;
    #(7*2);
    right = 1; #2; right = 0;
    #(5*2);
    right = 1; #2; right = 0;
    #(5*2);
    right = 1; #2; right = 0;
    #(6*2);
    right = 1; #2; right = 0;
    #(5*2);
    right = 1; #2; right = 0;
    #(27*2);
    shoot = 1; #2; shoot = 0;
    #(7*2);
    left = 1; #2; left = 0;
    #(19*2);
    left = 1; #2; left = 0;
    #(4*2);
    left = 1; #2; left = 0;
    #(5*2);
    left = 1; #2; left = 0;
    #(10*2);
    right = 1; #2; right = 0;
    #(11*2);
    shoot = 1; #2; shoot = 0;
    #(5*2);
    left = 1; #2; left = 0;
    #(4*2);
    left = 1; #2; left = 0;
    #(5*2);
    left = 1; #2; left = 0;
    #(4*2);
    left = 1; #2; left = 0;
    #(5*2);
    left = 1; #2; left = 0;
    #(4*2);
    left = 1; #2; left = 0;
    #(5*2);
    left = 1; #2; left = 0;
    #(38*2);
    shoot = 1; #2; shoot = 0;
    #(6*2);
    left = 1; #2; left = 0;
    #(5*2);
    left = 1; #2; left = 0;
    #(15*2);
    left = 1; #2; left = 0;
    #(12*2);
    shoot = 1; #2; shoot = 0;
    #(31*2);
    right = 1; #2; right = 0;
    #(5*2);
    right = 1; #2; right = 0;
    #(6*2);
    right = 1; #2; right = 0;
    #(4*2);
    right = 1; #2; right = 0;
    #(8*2);
    right = 1; #2; right = 0;
    #(5*2);
    right = 1; #2; right = 0;
    #(4*2);
    right = 1; #2; right = 0;
    #(5*2);
    right = 1; #2; right = 0;
    #(4*2);
    right = 1; #2; right = 0;
    #(6*2);
    right = 1; #2; right = 0;
    #(11*2);
    shoot = 1; #2; shoot = 0;
    #(13*2);
    right = 1; #2; right = 0;
    #(5*2);
    right = 1; #2; right = 0;
    #(5*2);
    right = 1; #2; right = 0;
    #(10*2);
    shoot = 1; #2; shoot = 0;
    #(20*2);
    left = 1; #2; left = 0;
    #(5*2);
    left = 1; #2; left = 0;
    #(5*2);
    left = 1; #2; left = 0;
    #(5*2);
    left = 1; #2; left = 0;
    #(4*2);
    left = 1; #2; left = 0;
    #(4*2);
    left = 1; #2; left = 0;
    #(18*2);
    left = 1; #2; left = 0;
    #(7*2);
    shoot = 1; #2; shoot = 0;
    #(19*2);
    right = 1; #2; right = 0;
    #(5*2);
    right = 1; #2; right = 0;
    #(5*2);
    right = 1; #2; right = 0;
    #(5*2);
    right = 1; #2; right = 0;
    #(10*2);
    shoot = 1; #2; shoot = 0;
    #(7*2);
    right = 1; #2; right = 0;
    #(4*2);
    right = 1; #2; right = 0;
    #(5*2);
    right = 1; #2; right = 0;
    #(7*2);
    shoot = 1; #2; shoot = 0;
    #(19*2);
    left = 1; #2; left = 0;
    #(6*2);
    left = 1; #2; left = 0;
    #(5*2);
    left = 1; #2; left = 0;
    #(4*2);
    left = 1; #2; left = 0;
    #(12*2);
    shoot = 1; #2; shoot = 0;
    #(10*2);
    left = 1; #2; left = 0;
    #(7*2);
    left = 1; #2; left = 0;
    #(12*2);
    right = 1; #2; right = 0;
    #(22*2);
    shoot = 1; #2; shoot = 0;
    #(6*2);
    left = 1; #2; left = 0;
    #(18*2);
    left = 1; #2; left = 0;
    #(5*2);
    left = 1; #2; left = 0;
    #(4*2);
    left = 1; #2; left = 0;
    #(4*2);
    left = 1; #2; left = 0;
    #(5*2);
    left = 1; #2; left = 0;
    #(3*2);
    left = 1; #2; left = 0;
    #(4*2);
    left = 1; #2; left = 0;
    #(4*2);
    left = 1; #2; left = 0;
    #(4*2);
    left = 1; #2; left = 0;
    #(5*2);
    left = 1; #2; left = 0;
    #(8*2);
    shoot = 1; #2; shoot = 0;
    #(6*2);
    right = 1; #2; right = 0;
    #(4*2);
    right = 1; #2; right = 0;
    #(5*2);
    right = 1; #2; right = 0;
    #(5*2);
    right = 1; #2; right = 0;
    #(5*2);
    right = 1; #2; right = 0;
    #(30*2);
    right = 1; #2; right = 0;
    #(7*2);
    right = 1; #2; right = 0;
    #(6*2);
    right = 1; #2; right = 0;
    #(6*2);
    right = 1; #2; right = 0;
    #(5*2);
    right = 1; #2; right = 0;
    #(19*2);
    left = 1; #2; left = 0;
    #(14*2);
    shoot = 1; #2; shoot = 0;
    #(7*2);
    right = 1; #2; right = 0;
    #(73*2);
    right = 1; #2; right = 0;
    #(5*2);
    right = 1; #2; right = 0;
    #(6*2);
    right = 1; #2; right = 0;
    #(8*2);
    right = 1; #2; right = 0;
    #(13*2);
    right = 1; #2; right = 0;
    #(12*2);
    right = 1; #2; right = 0;
    #(10*2);
    shoot = 1; #2; shoot = 0;
    #(21*2);
    left = 1; #2; left = 0;
    #(4*2);
    left = 1; #2; left = 0;
    #(5*2);
    left = 1; #2; left = 0;
    #(5*2);
    left = 1; #2; left = 0;
    #(4*2);
    left = 1; #2; left = 0;
    #(4*2);
    left = 1; #2; left = 0;
    #(6*2);
    left = 1; #2; left = 0;
    #(12*2);
    left = 1; #2; left = 0;
    #(5*2);
    shoot = 1; #2; shoot = 0;
    #(10*2);
    left = 1; #2; left = 0;
    #(5*2);
    left = 1; #2; left = 0;
    #(5*2);
    left = 1; #2; left = 0;
    #(4*2);
    left = 1; #2; left = 0;
    #(5*2);
    left = 1; #2; left = 0;
    #(4*2);
    left = 1; #2; left = 0;
    #(5*2);
    left = 1; #2; left = 0;
    #(5*2);
    left = 1; #2; left = 0;
    #(7*2);
    shoot = 1; #2; shoot = 0;
    #(14*2);
    right = 1; #2; right = 0;
    #(5*2);
    right = 1; #2; right = 0;
    #(4*2);
    right = 1; #2; right = 0;
    #(9*2);
    right = 1; #2; right = 0;
    #(5*2);
    right = 1; #2; right = 0;
    #(2000*2);
    $finish;
  end
endmodule

snapshot.vcd
$date
	Sun Nov 16 12:15:26 2025
$end
$version
	Icarus Verilog
$end
$timescale
	1ps
$end
$scope module snapshot_tb $end
$var wire 1 ! bullet_active $end
$var wire 5 " bullet_x [4:0] $end
$var wire 4 # bullet_y [3:0] $end
$var wire 1 $ enemy0_active $end
$var wire 5 % enemy0_x [4:0] $end
$var wire 4 & enemy0_y [3:0] $end
$var wire 1 ' enemy1_active $end
$var wire 5 ( enemy1_x [4:0] $end
$var wire 4 ) enemy1_y [3:0] $end
$var wire 1 * enemy2_active $end
$var wire 5 + enemy2_x [4:0] $end
$var wire 4 , enemy2_y [3:0] $end
$var wire 1 - hit $end
$var wire 8 . hit_count [7:0] $end
$var wire 5 / player_x [4:0] $end
$var wire 4 0 player_y [3:0] $end
$var wire 8 1 score [7:0] $end
$var reg 1 2 clk $end
$var integer 32 3 cycle [31:0] $end
$var reg 5 4 enemy_init_x [4:0] $end
$var reg 4 5 enemy_init_y [3:0] $end
$var reg 1 6 enemy_spawn $end
$var reg 1 7 left $end
$var reg 1 8 right $end
$var reg 1 9 rst_n $end
$var reg 1 : shoot $end
$scope module dut $end
$var wire 1 ; clk $end
$var wire 5 < enemy_init_x [4:0] $end
$var wire 4 = enemy_init_y [3:0] $end
$var wire 1 > enemy_spawn $end
$var wire 1 ? left $end
$var wire 1 @ right $end
$var wire 1 A rst_n $end
$var wire 1 B shoot $end
$var integer 32 C active_count [31:0] $end
$var reg 1 D bullet_active $end
$var reg 4 E bullet_timer_cnt [3:0] $end
$var reg 5 F bullet_x [4:0] $end
$var reg 4 G bullet_y [3:0] $end
$var reg 1 H enemy0_active $end
$var reg 4 I enemy0_timer_cnt [3:0] $end
$var reg 5 J enemy0_x [4:0] $end
$var reg 4 K enemy0_y [3:0] $end
$var reg 1 L enemy1_active $end
$var reg 4 M enemy1_timer_cnt [3:0] $end
$var reg 5 N enemy1_x [4:0] $end
$var reg 4 O enemy1_y [3:0] $end
$var reg 1 P enemy2_active $end
$var reg 4 Q enemy2_timer_cnt [3:0] $end
$var reg 5 R enemy2_x [4:0] $end
$var reg 4 S enemy2_y [3:0] $end
$var reg 1 T hit $end
$var reg 8 U hit_count [7:0] $end
$var reg 8 V lfsr [7:0] $end
$var reg 5 W player_x [4:0] $end
$var reg 4 X player_y [3:0] $end
$var reg 8 Y score [7:0] $end
$var reg 8 Z spawn_timer_cnt [7:0] $end
$upscope $end
$upscope $end
$enddefinitions $end
#0
$dumpvars
b0 Z
b0 Y
b1110 X
b1010 W
b10100101 V
b0 U
0T
b0 S
b0 R
b0 Q
0P
b0 O
b0 N
b0 M
0L
b0 K
b0 J
b0 I
0H
b0 G
b0 F
b0 E
0D
bx C
0B
0A
0@
0?
0>
b0 =
b0 <
0;
0:
09
08
07
06
b0 5
b0 4
bx 3
02
b0 1
b1110 0
b1010 /
b0 .
0-
b0 ,
b0 +
0*
b0 )
b0 (
0'
b0 &
b0 %
0$
b0 #
b0 "
0!
$end
#1000
12
1;
#2000
02
0;
#3000
12
1;
#4000
02
0;
#5000
b1 Z
b1001010 V
12
1;
19
1A
#6000
02
0;
#7000
b10 Z
b10010101 V
12
1;
b0 3
#8000
02
0;
#9000
b11 Z
b101010 V
12
1;
#10000
02
0;
#11000
b100 Z
b1010100 V
12
1;
#12000
02
0;
#13000
b101 Z
b10101001 V
12
1;
#14000
02
0;
#15000
b110 Z
b1010011 V
12
1;
#16000
02
0;
#17000
b111 Z
b10100111 V
12
1;
#18000
02
0;
#19000
b1000 Z
b1001110 V
12
1;
#20000
02
0;
#21000
b1001 Z
b10011101 V
12
1;
#22000
02
0;
#23000
b1010 Z
b111011 V
12
1;
#24000
02
0;
#25000
b111 J
b111 %
1H
1$
b0 Z
b1110111 V
b0 C
12
1;
#26000
02
0;
#27000
b1 I
b1 Z
b11101110 V
12
1;
#28000
02
0;
#29000
b10 I
b10 Z
b11011101 V
12
1;
#30000
02
0;
#31000
b1 K
b1 &
b0 I
b11 Z
b10111011 V
12
1;
#32000
02
0;
#33000
b1 I
b100 Z
b1110110 V
12
1;
#34000
02
0;
#35000
b10 I
b101 Z
b11101100 V
12
1;
#36000
02
0;
#37000
b10 K
b10 &
b0 I
b110 Z
b11011001 V
12
1;
#38000
02
0;
#39000
b1 I
b111 Z
b10110011 V
12
1;
#40000
02
0;
#41000
b10 I
b1000 Z
b1100111 V
12
1;
#42000
02
0;
#43000
b11 K
b11 &
b0 I
b1001 Z
b11001111 V
12
1;
#44000
02
0;
#45000
b1 I
b1010 Z
b10011110 V
12
1;
#46000
02
0;
#47000
b10 I
b1010 N
b1010 (
1L
1'
b0 Z
b111101 V
b1 C
12
1;
#48000
02
0;
#49000
b1 M
b100 K
b100 &
b0 I
b1 Z
b1111011 V
12
1;
#50000
02
0;
#51000
b10 M
b1 I
b10 Z
b11110111 V
12
1;
#52000
02
0;
#53000
b1 O
b1 )
b0 M
b10 I
b11 Z
b11101111 V
12
1;
#54000
02
0;
#55000
b1 M
b101 K
b101 &
b0 I
b100 Z
b11011111 V
12
1;
#56000
02
0;
#57000
b10 M
b1 I
b101 Z
b10111111 V
12
1;
#58000
02
0;
#59000
b10 O
b10 )
b0 M
b10 I
b110 Z
b1111110 V
12
1;
#60000
02
0;
#61000
b1 M
b110 K
b110 &
b0 I
b111 Z
b11111101 V
12
1;
#62000
02
0;
#63000
b10 M
b1 I
b1000 Z
b11111010 V
12
1;
#64000
02
0;
#65000
b11 O
b11 )
b0 M
b10 I
b1001 Z
b11110100 V
12
1;
#66000
02
0;
#67000
b1 M
b111 K
b111 &
b0 I
b1010 Z
b11101001 V
12
1;
#68000
02
0;
#69000
b10 M
b1 I
b1001 R
b1001 +
1P
1*
b0 Z
b11010011 V
b10 C
12
1;
#70000
02
0;
#71000
b1 Q
b100 O
b100 )
b0 M
b10 I
b1 Z
b10100110 V
12
1;
#72000
02
0;
#73000
b10 Q
b1 M
b1000 K
b1000 &
b0 I
b10 Z
b1001100 V
12
1;
#74000
02
0;
#75000
b1 S
b1 ,
b0 Q
b10 M
b1 I
b11 Z
b10011001 V
12
1;
#76000
02
0;
#77000
b1 Q
b101 O
b101 )
b0 M
b10 I
b100 Z
b110011 V
12
1;
#78000
02
0;
#79000
b10 Q
b1 M
b1001 K
b1001 &
b0 I
b101 Z
b1100110 V
12
1;
#80000
02
0;
#81000
b10 S
b10 ,
b0 Q
b10 M
b1 I
b110 Z
b11001101 V
12
1;
#82000
02
0;
#83000
b1 Q
b110 O
b110 )
b0 M
b10 I
b111 Z
b10011010 V
12
1;
#84000
02
0;
#85000
b10 Q
b1 M
b1010 K
b1010 &
b0 I
b1000 Z
b110101 V
12
1;
#86000
02
0;
#87000
b11 S
b11 ,
b0 Q
b10 M
b1 I
b1001 Z
b1101010 V
12
1;
#88000
02
0;
#89000
b1 Q
b111 O
b111 )
b0 M
b10 I
b1010 Z
b11010100 V
12
1;
#90000
02
0;
#91000
b10 Q
b1 M
b1011 K
b1011 &
b0 I
b0 Z
b10101000 V
b11 C
12
1;
#92000
02
0;
#93000
b100 S
b100 ,
b0 Q
b10 M
b1 I
b1 Z
b1010001 V
12
1;
#94000
02
0;
#95000
b1 Q
b1000 O
b1000 )
b0 M
b10 I
b10 Z
b10100011 V
12
1;
#96000
02
0;
#97000
b10 Q
b1 M
b1100 K
b1100 &
b0 I
b11 Z
b1001 W
b1001 /
b1000110 V
12
1;
17
1?
#98000
02
0;
#99000
b101 S
b101 ,
b0 Q
b10 M
b1 I
b100 Z
b10001100 V
12
1;
07
0?
#100000
02
0;
#101000
b1 Q
b1001 O
b1001 )
b0 M
b10 I
b101 Z
b11000 V
12
1;
#102000
02
0;
#103000
b10 Q
b1 M
b1101 K
b1101 &
b0 I
b110 Z
b110000 V
12
1;
#104000
02
0;
#105000
b110 S
b110 ,
b0 Q
b10 M
b1 I
b111 Z
b1100000 V
12
1;
#106000
02
0;
#107000
b1 Q
b1010 O
b1010 )
b0 M
b10 I
b1000 Z
b11000001 V
12
1;
#108000
02
0;
#109000
b10 Q
b1 M
b1110 K
b1110 &
b0 I
b1001 Z
b10000011 V
12
1;
#110000
02
0;
#111000
b111 S
b111 ,
b0 Q
b10 M
b1 I
b1010 Z
b111 V
12
1;
#112000
02
0;
#113000
b1 Q
b1011 O
b1011 )
b0 M
b10 I
b0 Z
b1110 V
b11 C
12
1;
#114000
02
0;
#115000
b10 Q
b1 M
0H
0$
b0 I
b1 Z
b11101 V
12
1;
#116000
02
0;
#117000
b1000 S
b1000 ,
b0 Q
b10 M
b10 Z
b1101 G
b1101 #
b1001 F
b1001 "
1D
1!
b111010 V
12
1;
1:
1B
#118000
02
0;
#119000
b1 Q
b1100 O
b1100 )
b0 M
b1 E
b11 Z
b1110101 V
12
1;
0:
0B
#120000
02
0;
#121000
b10 Q
b1 M
b1100 G
b1100 #
b0 E
b100 Z
b11101010 V
12
1;
#122000
02
0;
#123000
b1001 S
b1001 ,
b0 Q
b10 M
b1 E
b101 Z
b11010101 V
12
1;
#124000
02
0;
#125000
b1 Q
b1101 O
b1101 )
b0 M
b1011 G
b1011 #
b0 E
b110 Z
b10101010 V
12
1;
#126000
02
0;
#127000
b10 Q
b1 M
b1 E
b111 Z
b1010101 V
12
1;
#128000
02
0;
#129000
b1010 S
b1010 ,
b0 Q
b10 M
b1010 G
b1010 #
b0 E
b1000 Z
b10101011 V
12
1;
#130000
02
0;
#131000
b1 U
b1 .
b1 Y
b1 1
0P
0*
0D
0!
1T
1-
b1 Q
b1110 O
b1110 )
b0 M
b1 E
b1001 Z
b1010111 V
12
1;
#132000
02
0;
#133000
b1 M
b1010 Z
b10101111 V
0T
0-
12
1;
#134000
02
0;
#135000
b10 M
b0 K
b0 &
b1111 J
b1111 %
1H
1$
b0 Z
b1011111 V
b1 C
12
1;
#136000
02
0;
#137000
0L
0'
b0 M
b1 I
b1 Z
b10111110 V
12
1;
#138000
02
0;
#139000
b10 I
b10 Z
b1111100 V
12
1;
#140000
02
0;
#141000
b1 K
b1 &
b0 I
b11 Z
b11111001 V
12
1;
#142000
02
0;
#143000
b1 I
b100 Z
b1000 W
b1000 /
b11110010 V
12
1;
17
1?
#144000
02
0;
#145000
b10 I
b101 Z
b11100101 V
12
1;
07
0?
#146000
02
0;
#147000
b10 K
b10 &
b0 I
b110 Z
b11001010 V
12
1;
#148000
02
0;
#149000
b1 I
b111 Z
b10010100 V
12
1;
#150000
02
0;
#151000
b10 I
b1000 Z
b101000 V
12
1;
#152000
02
0;
#153000
b11 K
b11 &
b0 I
b1001 Z
b1010000 V
12
1;
#154000
02
0;
#155000
b1 I
b1010 Z
b10100001 V
12
1;
#156000
02
0;
#157000
b10 I
b0 O
b0 )
b1 N
b1 (
1L
1'
b0 Z
b1000010 V
b1 C
12
1;
#158000
02
0;
#159000
b1 M
b100 K
b100 &
b0 I
b1 Z
b0 E
b1101 G
b1101 #
b1000 F
b1000 "
1D
1!
b10000100 V
12
1;
1:
1B
#160000
02
0;
#161000
b10 M
b1 I
b1 E
b10 Z
b1001 V
12
1;
0:
0B
#162000
02
0;
#163000
b1 O
b1 )
b0 M
b10 I
b1100 G
b1100 #
b0 E
b11 Z
b10011 V
12
1;
#164000
02
0;
#165000
b1 M
b101 K
b101 &
b0 I
b1 E
b100 Z
b100111 V
12
1;
#166000
02
0;
#167000
b10 M
b1 I
b1011 G
b1011 #
b0 E
b101 Z
b1001111 V
12
1;
#168000
02
0;
#169000
b10 O
b10 )
b0 M
b10 I
b1 E
b110 Z
b10011111 V
12
1;
#170000
02
0;
#171000
b1 M
b110 K
b110 &
b0 I
b1010 G
b1010 #
b0 E
b111 Z
b111111 V
12
1;
#172000
02
0;
#173000
b10 M
b1 I
b1 E
b1000 Z
b1111111 V
12
1;
#174000
02
0;
#175000
b11 O
b11 )
b0 M
b10 I
b1001 G
b1001 #
b0 E
b1001 Z
b11111111 V
12
1;
#176000
02
0;
#177000
b1 M
b111 K
b111 &
b0 I
b1 E
b1010 Z
b11111110 V
12
1;
#178000
02
0;
#179000
b10 M
b1 I
b1000 G
b1000 #
b0 E
b0 Z
b11111100 V
b10 C
12
1;
#180000
02
0;
#181000
b100 O
b100 )
b0 M
b10 I
b1 E
b1 Z
b11111000 V
12
1;
#182000
02
0;
#183000
b1 M
b1000 K
b1000 &
b0 I
b111 G
b111 #
b0 E
b10 Z
b11110000 V
12
1;
#184000
02
0;
#185000
b10 M
b1 I
b1 E
b11 Z
b11100001 V
12
1;
#186000
02
0;
#187000
b101 O
b101 )
b0 M
b10 I
b110 G
b110 #
b0 E
b100 Z
b11000010 V
12
1;
#188000
02
0;
#189000
b1 M
b1001 K
b1001 &
b0 I
b1 E
b101 Z
b10000101 V
12
1;
#190000
02
0;
#191000
b10 M
b1 I
b101 G
b101 #
b0 E
b110 Z
b1011 V
12
1;
#192000
02
0;
#193000
b110 O
b110 )
b0 M
b10 I
b1 E
b111 Z
b10111 V
12
1;
#194000
02
0;
#195000
b1 M
b1010 K
b1010 &
b0 I
b100 G
b100 #
b0 E
b1000 Z
b101111 V
12
1;
#196000
02
0;
#197000
b10 M
b1 I
b1 E
b1001 Z
b1011110 V
12
1;
#198000
02
0;
#199000
b111 O
b111 )
b0 M
b10 I
b11 G
b11 #
b0 E
b1010 Z
b10111100 V
12
1;
#200000
02
0;
#201000
b1 M
b1011 K
b1011 &
b0 I
b1 E
b0 Z
b1111000 V
b10 C
12
1;
#202000
02
0;
#203000
b10 M
b1 I
b10 G
b10 #
b0 E
b1 Z
b11110001 V
12
1;
#204000
02
0;
#205000
b1000 O
b1000 )
b0 M
b10 I
b1 E
b10 Z
b11100011 V
12
1;
#206000
02
0;
#207000
b1 M
b1100 K
b1100 &
b0 I
b1 G
b1 #
b0 E
b11 Z
b11000110 V
12
1;
#208000
02
0;
#209000
b10 M
b1 I
b1 E
b100 Z
b10001101 V
12
1;
1:
1B
#210000
02
0;
#211000
b1001 O
b1001 )
b0 M
b10 I
b0 G
b0 #
b0 E
b101 Z
b11010 V
12
1;
0:
0B
#212000
02
0;
#213000
b1 M
b1101 K
b1101 &
b0 I
b1 E
b110 Z
b110100 V
12
1;
#214000
02
0;
#215000
b10 M
b1 I
0D
0!
b0 E
b111 Z
b1101000 V
12
1;
#216000
02
0;
#217000
b1010 O
b1010 )
b0 M
b10 I
b1000 Z
b11010000 V
12
1;
#218000
02
0;
#219000
b1 M
b1110 K
b1110 &
b0 I
b1001 Z
b10100000 V
12
1;
#220000
02
0;
#221000
b10 M
b1 I
b1010 Z
b1000000 V
12
1;
#222000
02
0;
#223000
b1011 O
b1011 )
b0 M
b10 I
b0 Z
b10000000 V
b10 C
12
1;
#224000
02
0;
#225000
b1 M
0H
0$
b0 I
b1 Z
b1 V
12
1;
#226000
02
0;
#227000
b10 M
b10 Z
b10 V
12
1;
#228000
02
0;
#229000
b1100 O
b1100 )
b0 M
b11 Z
b100 V
12
1;
#230000
02
0;
#231000
b1 M
b100 Z
b1000 V
12
1;
#232000
02
0;
#233000
b10 M
b101 Z
b10001 V
12
1;
#234000
02
0;
#235000
b1101 O
b1101 )
b0 M
b110 Z
b100011 V
12
1;
#236000
02
0;
